analogic/__cli__.py
analogic/__init__.py
analogic/analogic.py
analogic/analogic_tm1_service.py
analogic/authentication_provider.py
analogic/cam.py
analogic/camsecure.py
analogic/change_monitor.py
analogic/cli.py
analogic/core_endpoints.py
analogic/default_signal_receiver.py
analogic/email.py
analogic/endpoint.py
analogic/exceptions.py
analogic/json_log_formatter.py
analogic/loader.py
analogic/logging.json
analogic/loginbasic.py
analogic/logincam.py
analogic/long_running_task_executor.py
analogic/multi_authentication_provider.py
analogic/multi_authentication_provider_interface.py
analogic/multi_setting.py
analogic/nologin.py
analogic/pivot.py
analogic/request_logger.py
analogic/session_handler.py
analogic/setting.py
analogic/signal_receiver.py
analogic/signals.py
analogic/system_endpoints.py
analogic/task.py
analogic/version.config
analogic/version.py
analogic/new_app_structure/__init__.py
analogic/new_app_structure/app.json
analogic/new_app_structure/app.py
analogic/new_app_structure/server/Export.py
analogic/new_app_structure/server/Validation.py
analogic/new_app_structure/server/configs/custom_objects.json
analogic/new_app_structure/server/configs/repository.yml
analogic/new_app_structure/static/assets/js/configs/event-map.js
analogic/new_app_structure/static/assets/js/configs/repository.js
analogic/new_app_structure/static/assets/js/configs/widget-config.js
analogic/new_app_structure/static/assets/skin/css/ks-button-style.css
analogic/new_app_structure/static/assets/skin/css/ks-container-style.css
analogic/new_app_structure/static/assets/skin/css/ks-datepicker-style.css
analogic/new_app_structure/static/assets/skin/css/ks-dropbox-style.css
analogic/new_app_structure/static/assets/skin/css/ks-gauge-style.css
analogic/new_app_structure/static/assets/skin/css/ks-general.css
analogic/new_app_structure/static/assets/skin/css/ks-grid-cell-style.css
analogic/new_app_structure/static/assets/skin/css/ks-grid-row-style.css
analogic_framework-4.1.97.dist-info/licenses/LICENSE
analogic_framework-4.1.97.dist-info/METADATA
analogic_framework-4.1.97.dist-info/WHEEL
analogic_framework-4.1.97.dist-info/entry_points.txt
analogic_framework-4.1.97.dist-info/top_level.txt
analogic_framework-4.1.97.dist-info/RECORD
