Metadata-Version: 2.4
Name: analogic-framework
Version: 4.1.97
Author: 
Requires-Python: >=3.9
License-File: LICENSE
Requires-Dist: Flask==2.3.2
Requires-Dist: TM1py==2.1
Requires-Dist: PyJWT==2.4.0
Requires-Dist: requests==2.32.3
Requires-Dist: numpy==2.2.3
Requires-Dist: pandas==2.2.3
Requires-Dist: XlsxWriter==1.3.7
Requires-Dist: matplotlib==3.10.1
Requires-Dist: PyYaml==6.0
Requires-Dist: xlrd==2.0.1
Requires-Dist: openpyxl==3.1.5
Requires-Dist: json_logging==1.3.0
Requires-Dist: flask_talisman==1.1.0
Requires-Dist: Flask-APScheduler==1.12.4
Requires-Dist: orjson==3.9.15
Requires-Dist: rich==13.3.5
Requires-Dist: jproperties==2.1.1
Requires-Dist: cryptography<43.0.0,>=37.0.4
Dynamic: license-file
Dynamic: requires-dist
Dynamic: requires-python
